scrapyd/VERSION
scrapyd/__init__.py
scrapyd/_deprecate.py
scrapyd/app.py
scrapyd/config.py
scrapyd/default_scrapyd.conf
scrapyd/eggstorage.py
scrapyd/eggutils.py
scrapyd/environ.py
scrapyd/interfaces.py
scrapyd/launcher.py
scrapyd/poller.py
scrapyd/runner.py
scrapyd/scheduler.py
scrapyd/script.py
scrapyd/spiderqueue.py
scrapyd/sqlite.py
scrapyd/txapp.py
scrapyd/utils.py
scrapyd/webservice.py
scrapyd/website.py
scrapyd/scripts/__init__.py
scrapyd/scripts/scrapyd_run.py
scrapyd/tests/mybot.egg
scrapyd/tests/mybot2.egg
scrapyd/tests/mybot3.egg
scrapyd/tests/mybotunicode.egg
shannon_scrapyd-1.2.1.post3.dist-info/METADATA
shannon_scrapyd-1.2.1.post3.dist-info/RECORD
shannon_scrapyd-1.2.1.post3.dist-info/WHEEL
shannon_scrapyd-1.2.1.post3.dist-info/entry_points.txt
shannon_scrapyd-1.2.1.post3.dist-info/top_level.txt
