Metadata-Version: 2.1
Name: shannon-scrapyd
Version: 1.2.1.post3
Summary: Add nails to scrapyd foundation for alarm
Home-page: https://github.com/scrapy/scrapyd
Author: Scrapy developers
Maintainer: Scrapy developers
Maintainer-email: info@scrapy.org
License: BSD
Platform: UNKNOWN
Classifier: Programming Language :: Python
Classifier: Programming Language :: Python :: 2.7
Classifier: Programming Language :: Python :: 3
Classifier: Programming Language :: Python :: 3.4
Classifier: Programming Language :: Python :: 3.5
Classifier: Programming Language :: Python :: 3.6
Classifier: License :: OSI Approved :: BSD License
Classifier: Operating System :: OS Independent
Classifier: Development Status :: 5 - Production/Stable
Classifier: Environment :: Console
Classifier: Environment :: No Input/Output (Daemon)
Classifier: Topic :: Internet :: WWW/HTTP
Requires-Dist: Twisted (>=8.0)
Requires-Dist: Scrapy (>=1.0)
Requires-Dist: six
